  {
  "title": "Setting Up PostgreSQL (EL7)",
  "description": "Creating a new database cluster, setting up roles, creating databases, and standard settings",
  "difficulty": "beginner",
  "time": "20 minutes",
  "details": {
    "steps": [
      {"title": "Setting Up Package Repository", "text": "05-setup-repo.md"},
      {"title": "Setting Up The Default PG Instance", "text": "10-db-init.md"},
      {"title": "Initial Login", "text": "20-initial-login.md"},
      {"title": "PostgreSQL Host Based Authentication (pg_hba.conf)", "text": "30-pg_hba-conf.md"},
      {"title": "Creating Roles and Databases", "text": "40-create-roles-database.md"},
      {"title": "postgresql.conf Part 1 - Making changes", "text": "50-postgresql-conf-part1.md"},
      {"title": "postgresql.conf Part 2 - Connections & Memory", "text": "51-postgresql-conf-part2.md"},
      {"title": "postgresql.conf Part 3 - Replication & Write Ahead Log (WAL)", "text": "52-postgresql-conf-part3.md"},
      {"title": "postgresql.conf Part 4 - Logging", "text": "53-postgresql-conf-part4.md"}
    ],
    "intro": {
      "courseData": "env-init.sh",
      "code": "set-env.sh",
      "text": "intro.md",
      "credits": ""
    },
    "finish": {
      "text": "finish.md"
    }
  },
  "environment": {
    "uilayout": "terminal",
    "uimessage1": "\u001b[32mYour Interactive Bash Terminal.\u001b[m\r\n",
    "terminals": [
      {"name": "postgres_terminal", "target": "host01"}
    ]
  },
  "backend": {
    "imageid": "crunchydata-single1"
  }
}
